{
  "filename": "living_rooms_057.jpg",
  "source_url": "https://images.unsplash.com/photo-1554612292-c175942fb8c1?crop=entropy&cs=tinysrgb&fit=max&fm=jpg&ixid=M3w3NTg3OTJ8MHwxfHNlYXJjaHwxOHx8Y296eSUyMGxpdmluZyUyMHJvb218ZW58MXwwfHx8MTc0ODgyMzAyM3ww&ixlib=rb-4.1.0&q=80&w=1080",
  "source_id": "REdjtVaNyh8",
  "description": "Cermic store in Vikten, a tiny village located in Flakstad Municipality, Norway.",
  "author": "Rogério Toledo",
  "query": "cozy living room",
  "category": "living_rooms"
}